pymcsrvstatus/__init__.py
pymcsrvstatus/api.py
pymcsrvstatus/httpurl.py
pymcsrvstatus/missing.py
pymcsrvstatus/models.py
pymcsrvstatus/version.py
pymcsrvstatus-1.1.3.dist-info/METADATA
pymcsrvstatus-1.1.3.dist-info/WHEEL
pymcsrvstatus-1.1.3.dist-info/licenses/LICENSE.md
pymcsrvstatus-1.1.3.dist-info/RECORD
