Metadata-Version: 2.4
Name: pymcsrvstatus
Version: 1.1.3
Summary: An async API wrapper for the mcsrvstat.us API.
Project-URL: Homepage, https://c.csw.im/cswimr/pymcsrvstatus
Project-URL: Issues, https://c.csw.im/cswimr/pymcsrvstatus/issues
Project-URL: Source Archive, https://c.csw.im/cswimr/pymcsrvstatus/archive/c5dc01112824ae51d5d770d43008d95c8914200b.tar.gz
Author-email: cswimr <seaswimmertehfsh@gmail.com>
License-Expression: MPL-2.0
License-File: LICENSE.md
Classifier: Programming Language :: Python
Classifier: Programming Language :: Python :: 3.9
Classifier: Programming Language :: Python :: 3.10
Classifier: Programming Language :: Python :: 3.11
Requires-Python: >=3.9
Requires-Dist: aiohttp>=3.9.5
Requires-Dist: pydantic>=2.10.0
